bm25_chroma/__init__.py
bm25_chroma/bm25.py
bm25_chroma/hybrid_retriever.py
bm25_chroma-0.6.1.dist-info/licenses/LICENSE
tests/__init__.py
tests/test_examples.py
bm25_chroma-0.6.1.dist-info/METADATA
bm25_chroma-0.6.1.dist-info/WHEEL
bm25_chroma-0.6.1.dist-info/top_level.txt
bm25_chroma-0.6.1.dist-info/RECORD
