Metadata-Version: 2.4
Name: bm25-chroma
Version: 0.6.1
Summary: A fast, memory-efficient hybrid search system combining BM25 and vector search
Home-page: https://github.com/thistleknot/bm25-chroma
Author: Joshua Laferriere
Author-email: Your Name <your.email@example.com>
License: MIT
Project-URL: Homepage, https://github.com/thistleknot/bm25-chroma
Project-URL: Repository, https://github.com/thistleknot/bm25-chroma
Project-URL: Issues, https://github.com/thistleknot/bm25-chroma/issues
Classifier: Development Status :: 3 - Alpha
Classifier: Intended Audience :: Developers
Classifier: License :: OSI Approved :: MIT License
Classifier: Operating System :: OS Independent
Classifier: Programming Language :: Python :: 3
Classifier: Programming Language :: Python :: 3.8
Classifier: Programming Language :: Python :: 3.9
Classifier: Programming Language :: Python :: 3.10
Classifier: Programming Language :: Python :: 3.11
Classifier: Topic :: Scientific/Engineering :: Information Analysis
Classifier: Topic :: Text Processing :: Indexing
Requires-Python: >=3.8
License-File: LICENSE
Requires-Dist: chromadb>=0.4.0
Requires-Dist: nltk>=3.8
Requires-Dist: sentence-transformers>=2.2.0
Requires-Dist: tqdm>=4.64.0
Requires-Dist: numpy>=1.21.0
Provides-Extra: dev
Requires-Dist: pytest>=7.0; extra == "dev"
Requires-Dist: black>=22.0; extra == "dev"
Requires-Dist: flake8>=4.0; extra == "dev"
Requires-Dist: mypy>=0.950; extra == "dev"
Dynamic: author
Dynamic: home-page
Dynamic: license-file
Dynamic: requires-python
